dimet/__init__.py
dimet/__main__.py
dimet/config/__init__.py
dimet/config/analysis/method/abundance_plot.yaml
dimet/config/analysis/method/bivariate_analysis.yaml
dimet/config/analysis/method/differential_analysis.yaml
dimet/config/analysis/method/distr_fit_plot.yaml
dimet/config/analysis/method/isotopologue_proportions_plot.yaml
dimet/config/analysis/method/mean_enrichment_line_plot.yaml
dimet/config/analysis/method/metabologram_integration.yaml
dimet/config/analysis/method/multi_group_comparison.yaml
dimet/config/analysis/method/pca_analysis.yaml
dimet/config/analysis/method/pca_plot.yaml
dimet/config/analysis/method/time_course_analysis.yaml
dimet/config/config.yaml
dimet/config/hydra/help/dimet_help.yaml
dimet/constants.py
dimet/data/__init__.py
dimet/helpers.py
dimet/method/__init__.py
dimet/processing/__init__.py
dimet/processing/bivariate_analysis.py
dimet/processing/differential_analysis.py
dimet/processing/fit_statistical_distribution.py
dimet/processing/pca_analysis.py
dimet/visualization/.gitkeep
dimet/visualization/__init__.py
dimet/visualization/abundance_bars.py
dimet/visualization/distr_fit_plot.py
dimet/visualization/isotopologue_proportions.py
dimet/visualization/mean_enrichment_line_plot.py
dimet/visualization/metabologram.py
dimet/visualization/pca_plot.py
dimet-0.2.4.dist-info/LICENSE
dimet-0.2.4.dist-info/METADATA
dimet-0.2.4.dist-info/WHEEL
dimet-0.2.4.dist-info/RECORD
