Metadata-Version: 2.1
Name: DIMet
Version: 0.2.4
Summary: A tool for Differential analysis of Isotope-labeled targeted Metabolomics data
Home-page: https://github.com/cbib/DIMet.git
License: MIT
Author: Johanna Galvis Rodriguez
Author-email: deisy-johanna.galvis-rodriguez@u-bordeaux.fr
Maintainer: Benjamin Dartigues
Maintainer-email: benjamin.dartigues@u-bordeaux.fr
Requires-Python: >=3.9,<4.0
Classifier: License :: OSI Approved :: MIT License
Classifier: Programming Language :: Python :: 3
Classifier: Programming Language :: Python :: 3.9
Classifier: Programming Language :: Python :: 3.10
Classifier: Programming Language :: Python :: 3.11
Classifier: Programming Language :: Python :: 3.12
Requires-Dist: click (>=8.1.7,<9.0.0)
Requires-Dist: hydra-colorlog (>=1.2.0,<2.0.0)
Requires-Dist: hydra-core (>=1.3.2,<2.0.0)
Requires-Dist: numpy (>=1.26.4,<2.0.0)
Requires-Dist: pandas (>=2.2.0,<3.0.0)
Requires-Dist: pydantic (>=2.6.1,<3.0.0)
Requires-Dist: python-dotenv (>=1.0.1,<2.0.0)
Requires-Dist: pyyaml (>=6.0.1,<7.0.0)
Requires-Dist: scikit-learn (>=1.4.0,<2.0.0)
Requires-Dist: scipy (>=1.12.0,<2.0.0)
Requires-Dist: seaborn (>=0.13.2,<0.14.0)
Requires-Dist: statsmodels (>=0.14.1,<0.15.0)
Project-URL: Repository, https://github.com/cbib/DIMet.git
